Workbook

Sheet Übersicht
A1: INVESTITIONSRECHNUNG NORDDACH-PV
A3: Parameter | B3: Wert
A4: Investition | B4: =Annahmen!B14 | C4: Plan Wp | D4: max Wp
A5: Anlagengröße | B5: =Annahmen!B8 | C5: =D5/36*1000 | D5: =460*36/1000
A6: Jährlicher Ertrag (Jahr 1) - PVGIS | B6: =Annahmen!B10
A7: Spezifischer Ertrag - PVGIS | B7: =Annahmen!B9
A8: Strompreis | B8: =Annahmen!B18
A9: Einspeisevergütung (bis 10 kWp) | B9: =Annahmen!B19
A10: Einspeisevergütung (über 10 kWp) | B10: =Annahmen!B20
A12: ERGEBNISSE
A13: Amortisationszeit | B13: =VLOOKUP("JA", Jahresrechnung!N1:O27, 2, 0)
A14: Gesamtertrag 20 Jahre (nominal) | B14: =MAX(Jahresrechnung!L2:L22)
A15: Gesamtertrag 20 Jahre (kumuliert) | B15: =MAX(Jahresrechnung!L2:L22)-Annahmen!$B$14
A16: Kapitalwert 20 Jahre (NPV, 3% Diskont) | B16: =NPV(Annahmen!B39,(-1*Annahmen!B14),Jahresrechnung!J3:J22)
A17: Interner Zinsfuß 20 Jahre (IRR) | B17: =IRR(Jahresrechnung!J2:J22)
A18: Gesamtertrag 25 Jahre (nominal) | B18: =MAX(Jahresrechnung!L2:L27)
A19: Gesamtertrag 25 Jahre (kumuliert) | B19: =MAX(Jahresrechnung!L2:L27)-Annahmen!$B$14
A20: Kapitalwert 25 Jahre(NPV, 3% Diskont) | B20: =NPV(Annahmen!B39,(-1*Annahmen!B14),Jahresrechnung!J3:J27)
A21: Interner Zinsfuß 25 Jahre (IRR) | B21: =IRR(Jahresrechnung!J2:J27)
A23: INTERPRETATION
A24: Status | B24: ✓ Wirtschaftlich rentabel
A25: Bewertung | B25: ="Die Anlage amortisiert sich nach "&B13&" Jahren und erwirtschaftet über 25 Jahre einen Gewinn von "& ROUND(B19,2) & " € (nominal)."
B26: PVGIS-Simulation bestätigt mit 7,6% einen höheren Ertrag als konservativ geschätzt.
A27: Rendite | B27: ="Die interne Verzinsung von " & ROUND(B21*100,2) & "% liegt deutlich über der üblichen sicheren anlageformen und der inflationsrate."

Sheet Jahresrechnung
A1: Jahr | B1: PV-Ertrag (kWh) | C1: Stromverbrauch (kWh) | D1: Eigenverbrauch (kWh) | E1: Quote | F1: Einspeisung (kWh) | G1: Ersparnis EV (€) | H1: Einspeisevergütung (€) | I1: Betriebskosten (€) | J1: Jahresertrag netto (€) | K1: RoI | L1: Kumuliert (€) | M1: Diskontiert (€) | N1: Amortisation | O1: PV-Alt (kWh) | P1: EV-Alt (kWh) | Q1: Einspeisung-Alt (kWh) | R1: Ersparnis EV-Alt (€) | S1: Einspeisevergütung-Alt (€) | T1: Alt-Ertrag netto (€)
J2: =(-1)*Annahmen!B14
A3: 1 | B3: =Annahmen!$B$9*Annahmen!$B$8 | C3: 21000 | D3: =MIN(B3*E3,MAX(C3-P3,0)) | E3: 0.4 | F3: =MAX(B3-D3,0) | G3: =D3*Annahmen!$B$18 | H3: =F3 * ( (10/15) * Annahmen!$B$19 + (5/15) * Annahmen!$B$20 ) | I3: -150 | J3: =SUM(G3:I3)+T3 | K3: =J3/Annahmen!$B$14 | L3: =J3 | M3: =J3/(1+Annahmen!$B$39)^A3 | N3: =IF(L3>=Annahmen!$B$14,"JA","") | O3: =IF(A3<=Annahmen!$B$36,Annahmen!$B$33,0) | P3: =MIN(O3*Annahmen!$B$34,C3) | Q3: =MAX(O3-P3,0) | R3: =P3*Annahmen!$B$18 | S3: =Q3*Annahmen!$B$35 | T3: =SUM(R3:S3)
A4: 2 | B4: =B3*(1-Annahmen!$B$11) | C4: 21000 | D4: =MIN(B4*E4,MAX(C4-P4,0)) | E4: 0.4 | F4: =MAX(B4-D4,0) | G4: =D4*Annahmen!$B$18 | H4: =F4 * ( (10/15) * Annahmen!$B$19 + (5/15) * Annahmen!$B$20 ) | I4: -150 | J4: =SUM(G4:I4)+T4 | K4: =J4/Annahmen!$B$14 | L4: =L3+J4 | M4: =J4/(1+Annahmen!$B$39)^A4 | N4: =IF(L4>=Annahmen!$B$14,"JA","") | O4: =IF(A4<=Annahmen!$B$36,Annahmen!$B$33,0) | P4: =MIN(O4*Annahmen!$B$34,C4) | Q4: =MAX(O4-P4,0) | R4: =P4*Annahmen!$B$18 | S4: =Q4*Annahmen!$B$35 | T4: =SUM(R4:S4)
A5: 3 | B5: =B4*(1-Annahmen!$B$11) | C5: 21000 | D5: =MIN(B5*E5,MAX(C5-P5,0)) | E5: 0.4 | F5: =MAX(B5-D5,0) | G5: =D5*Annahmen!$B$18 | H5: =F5 * ( (10/15) * Annahmen!$B$19 + (5/15) * Annahmen!$B$20 ) | I5: -150 | J5: =SUM(G5:I5)+T5 | K5: =J5/Annahmen!$B$14 | L5: =L4+J5 | M5: =J5/(1+Annahmen!$B$39)^A5 | N5: =IF(L5>=Annahmen!$B$14,"JA","") | O5: =IF(A5<=Annahmen!$B$36,Annahmen!$B$33,0) | P5: =MIN(O5*Annahmen!$B$34,C5) | Q5: =MAX(O5-P5,0) | R5: =P5*Annahmen!$B$18 | S5: =Q5*Annahmen!$B$35 | T5: =SUM(R5:S5)
A6: 4 | B6: =B5*(1-Annahmen!$B$11) | C6: 21000 | D6: =MIN(B6*E6,MAX(C6-P6,0)) | E6: 0.4 | F6: =MAX(B6-D6,0) | G6: =D6*Annahmen!$B$18 | H6: =F6 * ( (10/15) * Annahmen!$B$19 + (5/15) * Annahmen!$B$20 ) | I6: -150 | J6: =SUM(G6:I6)+T6 | K6: =J6/Annahmen!$B$14 | L6: =L5+J6 | M6: =J6/(1+Annahmen!$B$39)^A6 | N6: =IF(L6>=Annahmen!$B$14,"JA","") | O6: =IF(A6<=Annahmen!$B$36,Annahmen!$B$33,0) | P6: =MIN(O6*Annahmen!$B$34,C6) | Q6: =MAX(O6-P6,0) | R6: =P6*Annahmen!$B$18 | S6: =Q6*Annahmen!$B$35 | T6: =SUM(R6:S6)
A7: 5 | B7: =B6*(1-Annahmen!$B$11) | C7: 21000 | D7: =MIN(B7*E7,MAX(C7-P7,0)) | E7: 0.4 | F7: =MAX(B7-D7,0) | G7: =D7*Annahmen!$B$18 | H7: =F7 * ( (10/15) * Annahmen!$B$19 + (5/15) * Annahmen!$B$20 ) | I7: -150 | J7: =SUM(G7:I7)+T7 | K7: =J7/Annahmen!$B$14 | L7: =L6+J7 | M7: =J7/(1+Annahmen!$B$39)^A7 | N7: =IF(L7>=Annahmen!$B$14,"JA","") | O7: =IF(A7<=Annahmen!$B$36,Annahmen!$B$33,0) | P7: =MIN(O7*Annahmen!$B$34,C7) | Q7: =MAX(O7-P7,0) | R7: =P7*Annahmen!$B$18 | S7: =Q7*Annahmen!$B$35 | T7: =SUM(R7:S7)
A8: 6 | B8: =B7*(1-Annahmen!$B$11) | C8: 18000 | D8: =MIN(B8*E8,MAX(C8-P8,0)) | E8: 0.35 | F8: =MAX(B8-D8,0) | G8: =D8*Annahmen!$B$18 | H8: =F8 * ( (10/15) * Annahmen!$B$19 + (5/15) * Annahmen!$B$20 ) | I8: -150 | J8: =SUM(G8:I8)+T8 | K8: =J8/Annahmen!$B$14 | L8: =L7+J8 | M8: =J8/(1+Annahmen!$B$39)^A8 | N8: =IF(L8>=Annahmen!$B$14,"JA","") | O8: =IF(A8<=Annahmen!$B$36,Annahmen!$B$33,0) | P8: =MIN(O8*Annahmen!$B$34,C8) | Q8: =MAX(O8-P8,0) | R8: =P8*Annahmen!$B$18 | S8: =Q8*Annahmen!$B$35 | T8: =SUM(R8:S8)
A9: 7 | B9: =B8*(1-Annahmen!$B$11) | C9: 18000 | D9: =MIN(B9*E9,MAX(C9-P9,0)) | E9: 0.35 | F9: =MAX(B9-D9,0) | G9: =D9*Annahmen!$B$18 | H9: =F9 * ( (10/15) * Annahmen!$B$19 + (5/15) * Annahmen!$B$20 ) | I9: -150 | J9: =SUM(G9:I9)+T9 | K9: =J9/Annahmen!$B$14 | L9: =L8+J9 | M9: =J9/(1+Annahmen!$B$39)^A9 | N9: =IF(L9>=Annahmen!$B$14,"JA","") | O9: =IF(A9<=Annahmen!$B$36,Annahmen!$B$33,0) | P9: =MIN(O9*Annahmen!$B$34,C9) | Q9: =MAX(O9-P9,0) | R9: =P9*Annahmen!$B$18 | S9: =Q9*Annahmen!$B$35 | T9: =SUM(R9:S9)
A10: 8 | B10: =B9*(1-Annahmen!$B$11) | C10: 18000 | D10: =MIN(B10*E10,MAX(C10-P10,0)) | E10: 0.35 | F10: =MAX(B10-D10,0) | G10: =D10*Annahmen!$B$18 | H10: =F10 * ( (10/15) * Annahmen!$B$19 + (5/15) * Annahmen!$B$20 ) | I10: -150 | J10: =SUM(G10:I10)+T10 | K10: =J10/Annahmen!$B$14 | L10: =L9+J10 | M10: =J10/(1+Annahmen!$B$39)^A10 | N10: =IF(L10>=Annahmen!$B$14,"JA","") | O10: =IF(A10<=Annahmen!$B$36,Annahmen!$B$33,0) | P10: =MIN(O10*Annahmen!$B$34,C10) | Q10: =MAX(O10-P10,0) | R10: =P10*Annahmen!$B$18 | S10: =Q10*Annahmen!$B$35 | T10: =SUM(R10:S10)
A11: 9 | B11: =B10*(1-Annahmen!$B$11) | C11: 18000 | D11: =MIN(B11*E11,MAX(C11-P11,0)) | E11: 0.35 | F11: =MAX(B11-D11,0) | G11: =D11*Annahmen!$B$18 | H11: =F11 * ( (10/15) * Annahmen!$B$19 + (5/15) * Annahmen!$B$20 ) | I11: -150 | J11: =SUM(G11:I11)+T11 | K11: =J11/Annahmen!$B$14 | L11: =L10+J11 | M11: =J11/(1+Annahmen!$B$39)^A11 | N11: =IF(L11>=Annahmen!$B$14,"JA","") | O11: =IF(A11<=Annahmen!$B$36,Annahmen!$B$33,0) | P11: =MIN(O11*Annahmen!$B$34,C11) | Q11: =MAX(O11-P11,0) | R11: =P11*Annahmen!$B$18 | S11: =Q11*Annahmen!$B$35 | T11: =SUM(R11:S11)
A12: 10 | B12: =B11*(1-Annahmen!$B$11) | C12: 18000 | D12: =MIN(B12*E12,MAX(C12-P12,0)) | E12: 0.35 | F12: =MAX(B12-D12,0) | G12: =D12*Annahmen!$B$18 | H12: =F12 * ( (10/15) * Annahmen!$B$19 + (5/15) * Annahmen!$B$20 ) | I12: -150 | J12: =SUM(G12:I12)+T12 | K12: =J12/Annahmen!$B$14 | L12: =L11+J12 | M12: =J12/(1+Annahmen!$B$39)^A12 | N12: =IF(L12>=Annahmen!$B$14,"JA","") | O12: =IF(A12<=Annahmen!$B$36,Annahmen!$B$33,0) | P12: =MIN(O12*Annahmen!$B$34,C12) | Q12: =MAX(O12-P12,0) | R12: =P12*Annahmen!$B$18 | S12: =Q12*Annahmen!$B$35 | T12: =SUM(R12:S12)
A13: 11 | B13: =B12*(1-Annahmen!$B$11) | C13: 15000 | D13: =MIN(B13*E13,MAX(C13-P13,0)) | E13: 0.3 | F13: =MAX(B13-D13,0) | G13: =D13*Annahmen!$B$18 | H13: =F13 * ( (10/15) * Annahmen!$B$19 + (5/15) * Annahmen!$B$20 ) | I13: -150 | J13: =SUM(G13:I13)+T13 | K13: =J13/Annahmen!$B$14 | L13: =L12+J13 | M13: =J13/(1+Annahmen!$B$39)^A13 | N13: =IF(L13>=Annahmen!$B$14,"JA","") | O13: =IF(A13<=Annahmen!$B$36,Annahmen!$B$33,0) | P13: =MIN(O13*Annahmen!$B$34,C13) | Q13: =MAX(O13-P13,0) | R13: =P13*Annahmen!$B$18 | S13: =Q13*Annahmen!$B$35 | T13: =SUM(R13:S13)
A14: 12 | B14: =B13*(1-Annahmen!$B$11) | C14: 15000 | D14: =MIN(B14*E14,MAX(C14-P14,0)) | E14: 0.3 | F14: =MAX(B14-D14,0) | G14: =D14*Annahmen!$B$18 | H14: =F14 * ( (10/15) * Annahmen!$B$19 + (5/15) * Annahmen!$B$20 ) | I14: -150 | J14: =SUM(G14:I14)+T14 | K14: =J14/Annahmen!$B$14 | L14: =L13+J14 | M14: =J14/(1+Annahmen!$B$39)^A14 | N14: =IF(L14>=Annahmen!$B$14,"JA","") | O14: =IF(A14<=Annahmen!$B$36,Annahmen!$B$33,0) | P14: =MIN(O14*Annahmen!$B$34,C14) | Q14: =MAX(O14-P14,0) | R14: =P14*Annahmen!$B$18 | S14: =Q14*Annahmen!$B$35 | T14: =SUM(R14:S14)
A15: 13 | B15: =B14*(1-Annahmen!$B$11) | C15: 15000 | D15: =MIN(B15*E15,MAX(C15-P15,0)) | E15: 0.3 | F15: =MAX(B15-D15,0) | G15: =D15*Annahmen!$B$18 | H15: =F15 * ( (10/15) * Annahmen!$B$19 + (5/15) * Annahmen!$B$20 ) | I15: -150 | J15: =SUM(G15:I15)+T15 | K15: =J15/Annahmen!$B$14 | L15: =L14+J15 | M15: =J15/(1+Annahmen!$B$39)^A15 | N15: =IF(L15>=Annahmen!$B$14,"JA","") | O15: =IF(A15<=Annahmen!$B$36,Annahmen!$B$33,0) | P15: =MIN(O15*Annahmen!$B$34,C15) | Q15: =MAX(O15-P15,0) | R15: =P15*Annahmen!$B$18 | S15: =Q15*Annahmen!$B$35 | T15: =SUM(R15:S15)
... A27: 25 | B27: =B26*(1-Annahmen!$B$11) | C27: 15005 | D27: =MIN(B27*E27,MAX(C27-P27,0)) | E27: 0.3 | F27: =MAX(B27-D27,0) | G27: =D27*Annahmen!$B$18 | H27: =F27 * ( (10/15) * Annahmen!$B$19 + (5/15) * Annahmen!$B$20 ) | I27: -145 | J27: =SUM(G27:I27)+T27 | K27: =J27/Annahmen!$B$14 | L27: =L26+J27 | M27: =J27/(1+Annahmen!$B$39)^A27 | N27: =IF(L27>=Annahmen!$B$14,"JA","") | O27: =IF(A27<=Annahmen!$B$36,Annahmen!$B$33,0) | P27: =MIN(O27*Annahmen!$B$34,C27) | Q27: =MAX(O27-P27,0) | R27: =P27*Annahmen!$B$18 | S27: =Q27*Annahmen!$B$35 | T27: =SUM(R27:S27)
N30: 2

Sheet Sensitivität
A1: SENSITIVITÄTSANALYSE: Amortisationszeit in Jahren
A3: Strompreis | B3: 0.8 | C3: 0.9 | D3: 1 | E3: 1.1 | F3: Ertrag der Anlage
A4: 0.25 | B4: =Annahmen!$B$14/((MIN((Annahmen!$B$10*B$3)*0.37,MAX(Jahresrechnung!$C$3-MIN((Annahmen!$B$33*B$3)*Annahmen!$B$34,Jahresrechnung!$C$3),0))*$A4 + MAX((Annahmen!$B$10*B$3)-MIN((Annahmen!$B$10*B$3)*0.37,MAX(Jahresrechnung!$C$3-MIN((Annahmen!$B$33*B$3)*Annahmen!$B$34,Jahresrechnung!$C$3),0)),0)*(Annahmen!$B$19*10/15+Annahmen!$B$20*5/15))-Annahmen!$B$15) | C4: =Annahmen!$B$14/((MIN((Annahmen!$B$10*C$3)*0.37,MAX(Jahresrechnung!$C$3-MIN((Annahmen!$B$33*C$3)*Annahmen!$B$34,Jahresrechnung!$C$3),0))*$A4 + MAX((Annahmen!$B$10*C$3)-MIN((Annahmen!$B$10*C$3)*0.37,MAX(Jahresrechnung!$C$3-MIN((Annahmen!$B$33*C$3)*Annahmen!$B$34,Jahresrechnung!$C$3),0)),0)*(Annahmen!$B$19*10/15+Annahmen!$B$20*5/15))-Annahmen!$B$15) | D4: =Annahmen!$B$14/((MIN((Annahmen!$B$10*D$3)*0.37,MAX(Jahresrechnung!$C$3-MIN((Annahmen!$B$33*D$3)*Annahmen!$B$34,Jahresrechnung!$C$3),0))*$A4 + MAX((Annahmen!$B$10*D$3)-MIN((Annahmen!$B$10*D$3)*0.37,MAX(Jahresrechnung!$C$3-MIN((Annahmen!$B$33*D$3)*Annahmen!$B$34,Jahresrechnung!$C$3),0)),0)*(Annahmen!$B$19*10/15+Annahmen!$B$20*5/15))-Annahmen!$B$15) | E4: =Annahmen!$B$14/((MIN((Annahmen!$B$10*E$3)*0.37,MAX(Jahresrechnung!$C$3-MIN((Annahmen!$B$33*E$3)*Annahmen!$B$34,Jahresrechnung!$C$3),0))*$A4 + MAX((Annahmen!$B$10*E$3)-MIN((Annahmen!$B$10*E$3)*0.37,MAX(Jahresrechnung!$C$3-MIN((Annahmen!$B$33*E$3)*Annahmen!$B$34,Jahresrechnung!$C$3),0)),0)*(Annahmen!$B$19*10/15+Annahmen!$B$20*5/15))-Annahmen!$B$15)
A5: 0.3 | B5: =Annahmen!$B$14/((MIN((Annahmen!$B$10*B$3)*0.37,MAX(Jahresrechnung!$C$3-MIN((Annahmen!$B$33*B$3)*Annahmen!$B$34,Jahresrechnung!$C$3),0))*$A5 + MAX((Annahmen!$B$10*B$3)-MIN((Annahmen!$B$10*B$3)*0.37,MAX(Jahresrechnung!$C$3-MIN((Annahmen!$B$33*B$3)*Annahmen!$B$34,Jahresrechnung!$C$3),0)),0)*(Annahmen!$B$19*10/15+Annahmen!$B$20*5/15))-Annahmen!$B$15) | C5: =Annahmen!$B$14/((MIN((Annahmen!$B$10*C$3)*0.37,MAX(Jahresrechnung!$C$3-MIN((Annahmen!$B$33*C$3)*Annahmen!$B$34,Jahresrechnung!$C$3),0))*$A5 + MAX((Annahmen!$B$10*C$3)-MIN((Annahmen!$B$10*C$3)*0.37,MAX(Jahresrechnung!$C$3-MIN((Annahmen!$B$33*C$3)*Annahmen!$B$34,Jahresrechnung!$C$3),0)),0)*(Annahmen!$B$19*10/15+Annahmen!$B$20*5/15))-Annahmen!$B$15) | D5: =Annahmen!$B$14/((MIN((Annahmen!$B$10*D$3)*0.37,MAX(Jahresrechnung!$C$3-MIN((Annahmen!$B$33*D$3)*Annahmen!$B$34,Jahresrechnung!$C$3),0))*$A5 + MAX((Annahmen!$B$10*D$3)-MIN((Annahmen!$B$10*D$3)*0.37,MAX(Jahresrechnung!$C$3-MIN((Annahmen!$B$33*D$3)*Annahmen!$B$34,Jahresrechnung!$C$3),0)),0)*(Annahmen!$B$19*10/15+Annahmen!$B$20*5/15))-Annahmen!$B$15) | E5: =Annahmen!$B$14/((MIN((Annahmen!$B$10*E$3)*0.37,MAX(Jahresrechnung!$C$3-MIN((Annahmen!$B$33*E$3)*Annahmen!$B$34,Jahresrechnung!$C$3),0))*$A5 + MAX((Annahmen!$B$10*E$3)-MIN((Annahmen!$B$10*E$3)*0.37,MAX(Jahresrechnung!$C$3-MIN((Annahmen!$B$33*E$3)*Annahmen!$B$34,Jahresrechnung!$C$3),0)),0)*(Annahmen!$B$19*10/15+Annahmen!$B$20*5/15))-Annahmen!$B$15)
A6: 0.32 | B6: =Annahmen!$B$14/((MIN((Annahmen!$B$10*B$3)*0.37,MAX(Jahresrechnung!$C$3-MIN((Annahmen!$B$33*B$3)*Annahmen!$B$34,Jahresrechnung!$C$3),0))*$A6 + MAX((Annahmen!$B$10*B$3)-MIN((Annahmen!$B$10*B$3)*0.37,MAX(Jahresrechnung!$C$3-MIN((Annahmen!$B$33*B$3)*Annahmen!$B$34,Jahresrechnung!$C$3),0)),0)*(Annahmen!$B$19*10/15+Annahmen!$B$20*5/15))-Annahmen!$B$15) | C6: =Annahmen!$B$14/((MIN((Annahmen!$B$10*C$3)*0.37,MAX(Jahresrechnung!$C$3-MIN((Annahmen!$B$33*C$3)*Annahmen!$B$34,Jahresrechnung!$C$3),0))*$A6 + MAX((Annahmen!$B$10*C$3)-MIN((Annahmen!$B$10*C$3)*0.37,MAX(Jahresrechnung!$C$3-MIN((Annahmen!$B$33*C$3)*Annahmen!$B$34,Jahresrechnung!$C$3),0)),0)*(Annahmen!$B$19*10/15+Annahmen!$B$20*5/15))-Annahmen!$B$15) | D6: =Annahmen!$B$14/((MIN((Annahmen!$B$10*D$3)*0.37,MAX(Jahresrechnung!$C$3-MIN((Annahmen!$B$33*D$3)*Annahmen!$B$34,Jahresrechnung!$C$3),0))*$A6 + MAX((Annahmen!$B$10*D$3)-MIN((Annahmen!$B$10*D$3)*0.37,MAX(Jahresrechnung!$C$3-MIN((Annahmen!$B$33*D$3)*Annahmen!$B$34,Jahresrechnung!$C$3),0)),0)*(Annahmen!$B$19*10/15+Annahmen!$B$20*5/15))-Annahmen!$B$15) | E6: =Annahmen!$B$14/((MIN((Annahmen!$B$10*E$3)*0.37,MAX(Jahresrechnung!$C$3-MIN((Annahmen!$B$33*E$3)*Annahmen!$B$34,Jahresrechnung!$C$3),0))*$A6 + MAX((Annahmen!$B$10*E$3)-MIN((Annahmen!$B$10*E$3)*0.37,MAX(Jahresrechnung!$C$3-MIN((Annahmen!$B$33*E$3)*Annahmen!$B$34,Jahresrechnung!$C$3),0)),0)*(Annahmen!$B$19*10/15+Annahmen!$B$20*5/15))-Annahmen!$B$15)
A7: 0.35 | B7: =Annahmen!$B$14/((MIN((Annahmen!$B$10*B$3)*0.37,MAX(Jahresrechnung!$C$3-MIN((Annahmen!$B$33*B$3)*Annahmen!$B$34,Jahresrechnung!$C$3),0))*$A7 + MAX((Annahmen!$B$10*B$3)-MIN((Annahmen!$B$10*B$3)*0.37,MAX(Jahresrechnung!$C$3-MIN((Annahmen!$B$33*B$3)*Annahmen!$B$34,Jahresrechnung!$C$3),0)),0)*(Annahmen!$B$19*10/15+Annahmen!$B$20*5/15))-Annahmen!$B$15) | C7: =Annahmen!$B$14/((MIN((Annahmen!$B$10*C$3)*0.37,MAX(Jahresrechnung!$C$3-MIN((Annahmen!$B$33*C$3)*Annahmen!$B$34,Jahresrechnung!$C$3),0))*$A7 + MAX((Annahmen!$B$10*C$3)-MIN((Annahmen!$B$10*C$3)*0.37,MAX(Jahresrechnung!$C$3-MIN((Annahmen!$B$33*C$3)*Annahmen!$B$34,Jahresrechnung!$C$3),0)),0)*(Annahmen!$B$19*10/15+Annahmen!$B$20*5/15))-Annahmen!$B$15) | D7: =Annahmen!$B$14/((MIN((Annahmen!$B$10*D$3)*0.37,MAX(Jahresrechnung!$C$3-MIN((Annahmen!$B$33*D$3)*Annahmen!$B$34,Jahresrechnung!$C$3),0))*$A7 + MAX((Annahmen!$B$10*D$3)-MIN((Annahmen!$B$10*D$3)*0.37,MAX(Jahresrechnung!$C$3-MIN((Annahmen!$B$33*D$3)*Annahmen!$B$34,Jahresrechnung!$C$3),0)),0)*(Annahmen!$B$19*10/15+Annahmen!$B$20*5/15))-Annahmen!$B$15) | E7: =Annahmen!$B$14/((MIN((Annahmen!$B$10*E$3)*0.37,MAX(Jahresrechnung!$C$3-MIN((Annahmen!$B$33*E$3)*Annahmen!$B$34,Jahresrechnung!$C$3),0))*$A7 + MAX((Annahmen!$B$10*E$3)-MIN((Annahmen!$B$10*E$3)*0.37,MAX(Jahresrechnung!$C$3-MIN((Annahmen!$B$33*E$3)*Annahmen!$B$34,Jahresrechnung!$C$3),0)),0)*(Annahmen!$B$19*10/15+Annahmen!$B$20*5/15))-Annahmen!$B$15)
A8: 0.4 | B8: =Annahmen!$B$14/((MIN((Annahmen!$B$10*B$3)*0.37,MAX(Jahresrechnung!$C$3-MIN((Annahmen!$B$33*B$3)*Annahmen!$B$34,Jahresrechnung!$C$3),0))*$A8 + MAX((Annahmen!$B$10*B$3)-MIN((Annahmen!$B$10*B$3)*0.37,MAX(Jahresrechnung!$C$3-MIN((Annahmen!$B$33*B$3)*Annahmen!$B$34,Jahresrechnung!$C$3),0)),0)*(Annahmen!$B$19*10/15+Annahmen!$B$20*5/15))-Annahmen!$B$15) | C8: =Annahmen!$B$14/((MIN((Annahmen!$B$10*C$3)*0.37,MAX(Jahresrechnung!$C$3-MIN((Annahmen!$B$33*C$3)*Annahmen!$B$34,Jahresrechnung!$C$3),0))*$A8 + MAX((Annahmen!$B$10*C$3)-MIN((Annahmen!$B$10*C$3)*0.37,MAX(Jahresrechnung!$C$3-MIN((Annahmen!$B$33*C$3)*Annahmen!$B$34,Jahresrechnung!$C$3),0)),0)*(Annahmen!$B$19*10/15+Annahmen!$B$20*5/15))-Annahmen!$B$15) | D8: =Annahmen!$B$14/((MIN((Annahmen!$B$10*D$3)*0.37,MAX(Jahresrechnung!$C$3-MIN((Annahmen!$B$33*D$3)*Annahmen!$B$34,Jahresrechnung!$C$3),0))*$A8 + MAX((Annahmen!$B$10*D$3)-MIN((Annahmen!$B$10*D$3)*0.37,MAX(Jahresrechnung!$C$3-MIN((Annahmen!$B$33*D$3)*Annahmen!$B$34,Jahresrechnung!$C$3),0)),0)*(Annahmen!$B$19*10/15+Annahmen!$B$20*5/15))-Annahmen!$B$15) | E8: =Annahmen!$B$14/((MIN((Annahmen!$B$10*E$3)*0.37,MAX(Jahresrechnung!$C$3-MIN((Annahmen!$B$33*E$3)*Annahmen!$B$34,Jahresrechnung!$C$3),0))*$A8 + MAX((Annahmen!$B$10*E$3)-MIN((Annahmen!$B$10*E$3)*0.37,MAX(Jahresrechnung!$C$3-MIN((Annahmen!$B$33*E$3)*Annahmen!$B$34,Jahresrechnung!$C$3),0)),0)*(Annahmen!$B$19*10/15+Annahmen!$B$20*5/15))-Annahmen!$B$15)
A10: Hinweise:
A11: ="• Basis-Szenario (32 ct/kWh, 100% Ertrag): "&ROUND(D6,2)&" Jahre Amortisation (PVGIS-Daten: 7,2 Jahre)"
A12: • Bei sinkendem Verbrauch (Kinder ziehen aus) verschlechtert sich die Wirtschaftlichkeit leicht
A13: • Bei steigenden Strompreisen amortisiert sich die Anlage deutlich schneller
A14: • Selbst bei nur 80% des erwarteten Ertrags liegt die Amortisation unter 15 Jahren

Sheet Annahmen
A1: DETAILLIERTE ANNAHMEN DER BERECHNUNG
A3: Standort & Anlage
A4: PLZ | B4: 55545 (Bad Kreuznach)
A5: Dachausrichtung | B5: Nord-Nord-Ost (24° West)
A6: Dachneigung | B6: 30°
A7: Verfügbare Dachfläche | B7: ca. 100 m² (effektiv ~80 m² nutzbar)
A8: Installierte Leistung | B8: =Übersicht!D5 | C8: 15.48
A9: Spezifischer Ertrag (PVGIS / Jahr) | B9: 753
A10: Jährlicher Ertrag (Jahr 1) | B10: 11297
A11: Degradation pro Jahr | B11: 0.005
A13: Kosten
A14: Investitionskosten (1.300 €/kWp, Vollinstallation) | B14: 18007.88
A15: Betriebskosten pro Jahr (Wartung, Versicherung) | B15: 150
A17: Vergütung & Preise
A18: Strompreis (Bezug) | B18: 0.32
A19: Einspeisevergütung (0-10 kWp) | B19: 0.0778
A20: Einspeisevergütung (>10 kWp) | B20: 0.0673
A22: Verbrauchsszenarien
A23: Jahre 1-5 | B23: 21.000 kWh (WP 7.500 + Autos 9.000 + Haushalt 4.500)
B24: Eigenverbrauchsquote: 40%
A25: Jahre 6-10 | B25: 18.000 kWh (WP 7.500 + Autos 6.000 + Haushalt 4.500)
B26: Eigenverbrauchsquote: 35%
A27: Jahre 11-20 | B27: 15.000 kWh (WP 7.500 + Autos 3.000 + Haushalt 4.500)
B28: Eigenverbrauchsquote: 30%
A30: Bestandsanlage (Südseite)
A31: Installierte Leistung | B31: 11.28
A32: Inbetriebnahme | B32: 2012
A33: Jährlicher Ertrag | B33: 12000
A34: Eigenverbrauch (kein Akku) | B34: 0.3
A35: Einspeisevergütung | B35: 0.18
A36: Restlaufzeit | B36: =2013+20-YEAR(TODAY())
A38: Finanzielle Parameter
A39: Diskontierungssatz | B39: 0.03
A40: Betrachtungszeitraum | B40: 20
A41: Inflationsanpassung | B41: nicht berücksichtigt (konservativ)
