Workbook

Sheet Übersicht
A1: INVESTITIONSRECHNUNG NORDDACH-PV
A3: Parameter | B3: Wert
A4: Investition | B4: =Annahmen!B14 -> 18007.88 | C4: Plan Wp | D4: max Wp
A5: Anlagengröße | B5: =Annahmen!B8 -> 16.56 | C5: =D5/36*1000 -> 460 | D5: =460*36/1000 -> 16.56
A6: Jährlicher Ertrag (Jahr 1) - PVGIS | B6: =Annahmen!B10 -> 11297
A7: Spezifischer Ertrag - PVGIS | B7: =Annahmen!B9 -> 753
A8: Strompreis | B8: =Annahmen!B18 -> 0.32
A9: Einspeisevergütung (bis 10 kWp) | B9: =Annahmen!B19 -> 0.0778
A10: Einspeisevergütung (über 10 kWp) | B10: =Annahmen!B20 -> 0.0673
A12: ERGEBNISSE
A13: Amortisationszeit | B13: =VLOOKUP("JA", Jahresrechnung!N1:O27, 2, 0) -> 10
A14: Gesamtertrag 20 Jahre (nominal) | B14: =MAX(Jahresrechnung!L2:L22) -> 34467.109
A15: Gesamtertrag 20 Jahre (kumuliert) | B15: =MAX(Jahresrechnung!L2:L22)-Annahmen!$B$14 -> 16459.229
A16: Kapitalwert 20 Jahre (NPV, 3% Diskont) | B16: =NPV(Annahmen!B39,(-1*Annahmen!B14),Jahresrechnung!J3:J22) -> 7820.8047
A17: Interner Zinsfuß 20 Jahre (IRR) | B17: =IRR(Jahresrechnung!J2:J22) -> 0.077064379
A18: Gesamtertrag 25 Jahre (nominal) | B18: =MAX(Jahresrechnung!L2:L27) -> 41996.96
A19: Gesamtertrag 25 Jahre (kumuliert) | B19: =MAX(Jahresrechnung!L2:L27)-Annahmen!$B$14 -> 23989.08
A20: Kapitalwert 25 Jahre(NPV, 3% Diskont) | B20: =NPV(Annahmen!B39,(-1*Annahmen!B14),Jahresrechnung!J3:J27) -> 11529.29
A21: Interner Zinsfuß 25 Jahre (IRR) | B21: =IRR(Jahresrechnung!J2:J27) -> 0.086412572
A23: INTERPRETATION
A24: Status | B24: ✓ Wirtschaftlich rentabel
A25: Bewertung | B25: ="Die Anlage amortisiert sich nach "&B13&" Jahren und erwirtschaftet über 25 Jahre einen Gewinn von "& ROUND(B19,2) & " € (nominal)." -> Die Anlage amortisiert sich nach 10 Jahren und erwirtschaftet über 25 Jahre einen Gewinn von 23989,08 € (nominal).
B26: PVGIS-Simulation bestätigt mit 7,6% einen höheren Ertrag als konservativ geschätzt.
A27: Rendite | B27: ="Die interne Verzinsung von " & ROUND(B21*100,2) & "% liegt deutlich über der üblichen sicheren anlageformen und der inflationsrate." -> Die interne Verzinsung von 8,64% liegt deutlich über der üblichen sicheren anlageformen und der inflationsrate.

Sheet Jahresrechnung
A1: Jahr | B1: PV-Ertrag (kWh) | C1: Stromverbrauch (kWh) | D1: Eigenverbrauch (kWh) | E1: Quote | F1: Einspeisung (kWh) | G1: Ersparnis EV (€) | H1: Einspeisevergütung (€) | I1: Betriebskosten (€) | J1: Jahresertrag netto (€) | K1: RoI | L1: Kumuliert (€) | M1: Diskontiert (€) | N1: Amortisation
J2: =(-1)*Annahmen!B14 -> -18007.88
A3: 1 | B3: =Annahmen!$B$9*Annahmen!$B$8 -> 12469.68 | C3: 21000 | D3: =B3*E3 -> 4987.872 | E3: 0.4 | F3: =IF(B3-D3<0,0,B3-D3) -> 7481.808 | G3: =D3*Annahmen!$B$18 -> 1596.119 | H3: =F3 * ( (10/15) * Annahmen!$B$19 + (5/15) * Annahmen!$B$20 ) -> 555.89833 | I3: -150 | J3: =SUM(G3:I3) -> 2002.0174 | K3: =J3/Annahmen!$B$14 -> 0.11117452 | L3: =J3 -> 2002.0174 | M3: =J3/(1+Annahmen!$B$39)^A3 -> 1943.7062 | N3: =IF(L3>=Annahmen!$B$14,"JA","") | O3: =A3 -> 1
A4: 2 | B4: =B3*(1-Annahmen!$B$11) -> 12407.332 | C4: 21000 | D4: =B4*E4 -> 4962.9326 | E4: 0.4 | F4: =IF(B4-D4<0,0,B4-D4) -> 7444.399 | G4: =D4*Annahmen!$B$18 -> 1588.1384 | H4: =F4 * ( (10/15) * Annahmen!$B$19 + (5/15) * Annahmen!$B$20 ) -> 553.11884 | I4: -150 | J4: =SUM(G4:I4) -> 1991.2573 | K4: =J4/Annahmen!$B$14 -> 0.110577 | L4: =L3+J4 -> 3993.2747 | M4: =J4/(1+Annahmen!$B$39)^A4 -> 1876.951 | N4: =IF(L4>=Annahmen!$B$14,"JA","") | O4: =A4 -> 2
A5: 3 | B5: =B4*(1-Annahmen!$B$11) -> 12345.295 | C5: 21000 | D5: =B5*E5 -> 4938.118 | E5: 0.4 | F5: =IF(B5-D5<0,0,B5-D5) -> 7407.177 | G5: =D5*Annahmen!$B$18 -> 1580.1978 | H5: =F5 * ( (10/15) * Annahmen!$B$19 + (5/15) * Annahmen!$B$20 ) -> 550.35325 | I5: -150 | J5: =SUM(G5:I5) -> 1980.551 | K5: =J5/Annahmen!$B$14 -> 0.10998246 | L5: =L4+J5 -> 5973.8257 | M5: =J5/(1+Annahmen!$B$39)^A5 -> 1812.4847 | N5: =IF(L5>=Annahmen!$B$14,"JA","") | O5: =A5 -> 3
A6: 4 | B6: =B5*(1-Annahmen!$B$11) -> 12283.568 | C6: 21000 | D6: =B6*E6 -> 4913.4274 | E6: 0.4 | F6: =IF(B6-D6<0,0,B6-D6) -> 7370.1411 | G6: =D6*Annahmen!$B$18 -> 1572.2968 | H6: =F6 * ( (10/15) * Annahmen!$B$19 + (5/15) * Annahmen!$B$20 ) -> 547.60148 | I6: -150 | J6: =SUM(G6:I6) -> 1969.8982 | K6: =J6/Annahmen!$B$14 -> 0.1093909 | L6: =L5+J6 -> 7943.7239 | M6: =J6/(1+Annahmen!$B$39)^A6 -> 1750.2291 | N6: =IF(L6>=Annahmen!$B$14,"JA","") | O6: =A6 -> 4
A7: 5 | B7: =B6*(1-Annahmen!$B$11) -> 12222.151 | C7: 21000 | D7: =B7*E7 -> 4888.8602 | E7: 0.4 | F7: =IF(B7-D7<0,0,B7-D7) -> 7333.2904 | G7: =D7*Annahmen!$B$18 -> 1564.4353 | H7: =F7 * ( (10/15) * Annahmen!$B$19 + (5/15) * Annahmen!$B$20 ) -> 544.86347 | I7: -150 | J7: =SUM(G7:I7) -> 1959.2988 | K7: =J7/Annahmen!$B$14 -> 0.1088023 | L7: =L6+J7 -> 9903.0227 | M7: =J7/(1+Annahmen!$B$39)^A7 -> 1690.1083 | N7: =IF(L7>=Annahmen!$B$14,"JA","") | O7: =A7 -> 5
A8: 6 | B8: =B7*(1-Annahmen!$B$11) -> 12161.04 | C8: 18000 | D8: =B8*E8 -> 4256.364 | E8: 0.35 | F8: =IF(B8-D8<0,0,B8-D8) -> 7904.6759 | G8: =D8*Annahmen!$B$18 -> 1362.0365 | H8: =F8 * ( (10/15) * Annahmen!$B$19 + (5/15) * Annahmen!$B$20 ) -> 587.31742 | I8: -150 | J8: =SUM(G8:I8) -> 1799.3539 | K8: =J8/Annahmen!$B$14 -> 0.099920362 | L8: =L7+J8 -> 11702.377 | M8: =J8/(1+Annahmen!$B$39)^A8 -> 1506.9306 | N8: =IF(L8>=Annahmen!$B$14,"JA","") | O8: =A8 -> 6
A9: 7 | B9: =B8*(1-Annahmen!$B$11) -> 12100.235 | C9: 18000 | D9: =B9*E9 -> 4235.0821 | E9: 0.35 | F9: =IF(B9-D9<0,0,B9-D9) -> 7865.1525 | G9: =D9*Annahmen!$B$18 -> 1355.2263 | H9: =F9 * ( (10/15) * Annahmen!$B$19 + (5/15) * Annahmen!$B$20 ) -> 584.38083 | I9: -150 | J9: =SUM(G9:I9) -> 1789.6071 | K9: =J9/Annahmen!$B$14 -> 0.099379112 | L9: =L8+J9 -> 13491.984 | M9: =J9/(1+Annahmen!$B$39)^A9 -> 1455.1144 | N9: =IF(L9>=Annahmen!$B$14,"JA","") | O9: =A9 -> 7
A10: 8 | B10: =B9*(1-Annahmen!$B$11) -> 12039.733 | C10: 18000 | D10: =B10*E10 -> 4213.9067 | E10: 0.35 | F10: =IF(B10-D10<0,0,B10-D10) -> 7825.8268 | G10: =D10*Annahmen!$B$18 -> 1348.4502 | H10: =F10 * ( (10/15) * Annahmen!$B$19 + (5/15) * Annahmen!$B$20 ) -> 581.45893 | I10: -150 | J10: =SUM(G10:I10) -> 1779.9091 | K10: =J10/Annahmen!$B$14 -> 0.098840568 | L10: =L9+J10 -> 15271.893 | M10: =J10/(1+Annahmen!$B$39)^A10 -> 1405.0767 | N10: =IF(L10>=Annahmen!$B$14,"JA","") | O10: =A10 -> 8
A11: 9 | B11: =B10*(1-Annahmen!$B$11) -> 11979.535 | C11: 18000 | D11: =B11*E11 -> 4192.8372 | E11: 0.35 | F11: =IF(B11-D11<0,0,B11-D11) -> 7786.6976 | G11: =D11*Annahmen!$B$18 -> 1341.7079 | H11: =F11 * ( (10/15) * Annahmen!$B$19 + (5/15) * Annahmen!$B$20 ) -> 578.55163 | I11: -150 | J11: =SUM(G11:I11) -> 1770.2595 | K11: =J11/Annahmen!$B$14 -> 0.098304716 | L11: =L10+J11 -> 17042.152 | M11: =J11/(1+Annahmen!$B$39)^A11 -> 1356.7565 | N11: =IF(L11>=Annahmen!$B$14,"JA","") | O11: =A11 -> 9
A12: 10 | B12: =B11*(1-Annahmen!$B$11) -> 11919.637 | C12: 18000 | D12: =B12*E12 -> 4171.873 | E12: 0.35 | F12: =IF(B12-D12<0,0,B12-D12) -> 7747.7642 | G12: =D12*Annahmen!$B$18 -> 1334.9994 | H12: =F12 * ( (10/15) * Annahmen!$B$19 + (5/15) * Annahmen!$B$20 ) -> 575.65888 | I12: -150 | J12: =SUM(G12:I12) -> 1760.6582 | K12: =J12/Annahmen!$B$14 -> 0.097771544 | L12: =L11+J12 -> 18802.811 | M12: =J12/(1+Annahmen!$B$39)^A12 -> 1310.0951 | N12: =IF(L12>=Annahmen!$B$14,"JA","") -> JA | O12: =A12 -> 10
A13: 11 | B13: =B12*(1-Annahmen!$B$11) -> 11860.039 | C13: 15000 | D13: =B13*E13 -> 3558.0117 | E13: 0.3 | F13: =IF(B13-D13<0,0,B13-D13) -> 8302.0273 | G13: =D13*Annahmen!$B$18 -> 1138.5637 | H13: =F13 * ( (10/15) * Annahmen!$B$19 + (5/15) * Annahmen!$B$20 ) -> 616.84063 | I13: -150 | J13: =SUM(G13:I13) -> 1605.4044 | K13: =J13/Annahmen!$B$14 -> 0.089150104 | L13: =L12+J13 -> 20408.215 | M13: =J13/(1+Annahmen!$B$39)^A13 -> 1159.7783 | N13: =IF(L13>=Annahmen!$B$14,"JA","") -> JA | O13: =A13 -> 11
A14: 12 | B14: =B13*(1-Annahmen!$B$11) -> 11800.739 | C14: 15000 | D14: =B14*E14 -> 3540.2216 | E14: 0.3 | F14: =IF(B14-D14<0,0,B14-D14) -> 8260.5171 | G14: =D14*Annahmen!$B$18 -> 1132.8709 | H14: =F14 * ( (10/15) * Annahmen!$B$19 + (5/15) * Annahmen!$B$20 ) -> 613.75642 | I14: -150 | J14: =SUM(G14:I14) -> 1596.6273 | K14: =J14/Annahmen!$B$14 -> 0.088662705 | L14: =L13+J14 -> 22004.842 | M14: =J14/(1+Annahmen!$B$39)^A14 -> 1119.8423 | N14: =IF(L14>=Annahmen!$B$14,"JA","") -> JA | O14: =A14 -> 12
A15: 13 | B15: =B14*(1-Annahmen!$B$11) -> 11741.735 | C15: 15000 | D15: =B15*E15 -> 3522.5205 | E15: 0.3 | F15: =IF(B15-D15<0,0,B15-D15) -> 8219.2146 | G15: =D15*Annahmen!$B$18 -> 1127.2066 | H15: =F15 * ( (10/15) * Annahmen!$B$19 + (5/15) * Annahmen!$B$20 ) -> 610.68764 | I15: -150 | J15: =SUM(G15:I15) -> 1587.8942 | K15: =J15/Annahmen!$B$14 -> 0.088177743 | L15: =L14+J15 -> 23592.736 | M15: =J15/(1+Annahmen!$B$39)^A15 -> 1081.2787 | N15: =IF(L15>=Annahmen!$B$14,"JA","") -> JA | O15: =A15 -> 13
... A27: 25 | B27: =B26*(1-Annahmen!$B$11) -> 11056.286 | C27: 15005 | D27: =B27*E27 -> 3316.8857 | E27: 0.3 | F27: =IF(B27-D27<0,0,B27-D27) -> 7739.3999 | G27: =D27*Annahmen!$B$18 -> 1061.4034 | H27: =F27 * ( (10/15) * Annahmen!$B$19 + (5/15) * Annahmen!$B$20 ) -> 575.03741 | I27: -145 | J27: =SUM(G27:I27) -> 1491.4408 | K27: =J27/Annahmen!$B$14 -> 0.082821566 | L27: =L26+J27 -> 41996.96 | M27: =J27/(1+Annahmen!$B$39)^A27 -> 712.32044 | N27: =IF(L27>=Annahmen!$B$14,"JA","") -> JA | O27: =A27 -> 25
N30: 2

Sheet Sensitivität
A1: SENSITIVITÄTSANALYSE: Amortisationszeit in Jahren
A3: Strompreis | B3: 0.8 | C3: 0.9 | D3: 1 | E3: 1.1 | F3: Ertrag der Anlage
A4: 0.25 | B4: =Annahmen!$B$14/((Annahmen!$B$10*B$3*(0.37*$A4+0.63*(Annahmen!$B$19*10/15+Annahmen!$B$20*5/15)))-Annahmen!$B$15) -> 16.237666 | C4: =Annahmen!$B$14/((Annahmen!$B$10*C$3*(0.37*$A4+0.63*(Annahmen!$B$19*10/15+Annahmen!$B$20*5/15)))-Annahmen!$B$15) -> 14.219781 | D4: =Annahmen!$B$14/((Annahmen!$B$10*D$3*(0.37*$A4+0.63*(Annahmen!$B$19*10/15+Annahmen!$B$20*5/15)))-Annahmen!$B$15) -> 12.647992 | E4: =Annahmen!$B$14/((Annahmen!$B$10*E$3*(0.37*$A4+0.63*(Annahmen!$B$19*10/15+Annahmen!$B$20*5/15)))-Annahmen!$B$15) -> 11.389095
A5: 0.3 | B5: =Annahmen!$B$14/((Annahmen!$B$10*B$3*(0.37*$A5+0.63*(Annahmen!$B$19*10/15+Annahmen!$B$20*5/15)))-Annahmen!$B$15) -> 14.110385 | C5: =Annahmen!$B$14/((Annahmen!$B$10*C$3*(0.37*$A5+0.63*(Annahmen!$B$19*10/15+Annahmen!$B$20*5/15)))-Annahmen!$B$15) -> 12.380877 | D5: =Annahmen!$B$14/((Annahmen!$B$10*D$3*(0.37*$A5+0.63*(Annahmen!$B$19*10/15+Annahmen!$B$20*5/15)))-Annahmen!$B$15) -> 11.029048 | E5: =Annahmen!$B$14/((Annahmen!$B$10*E$3*(0.37*$A5+0.63*(Annahmen!$B$19*10/15+Annahmen!$B$20*5/15)))-Annahmen!$B$15) -> 9.9433636
A6: 0.32 | B6: =Annahmen!$B$14/((Annahmen!$B$10*B$3*(0.37*$A6+0.63*(Annahmen!$B$19*10/15+Annahmen!$B$20*5/15)))-Annahmen!$B$15) -> 13.40777 | C6: =Annahmen!$B$14/((Annahmen!$B$10*C$3*(0.37*$A6+0.63*(Annahmen!$B$19*10/15+Annahmen!$B$20*5/15)))-Annahmen!$B$15) -> 11.771938 | D6: =Annahmen!$B$14/((Annahmen!$B$10*D$3*(0.37*$A6+0.63*(Annahmen!$B$19*10/15+Annahmen!$B$20*5/15)))-Annahmen!$B$15) -> 10.491864 | E6: =Annahmen!$B$14/((Annahmen!$B$10*E$3*(0.37*$A6+0.63*(Annahmen!$B$19*10/15+Annahmen!$B$20*5/15)))-Annahmen!$B$15) -> 9.4628768
A7: 0.35 | B7: =Annahmen!$B$14/((Annahmen!$B$10*B$3*(0.37*$A7+0.63*(Annahmen!$B$19*10/15+Annahmen!$B$20*5/15)))-Annahmen!$B$15) -> 12.475927 | C7: =Annahmen!$B$14/((Annahmen!$B$10*C$3*(0.37*$A7+0.63*(Annahmen!$B$19*10/15+Annahmen!$B$20*5/15)))-Annahmen!$B$15) -> 10.963124 | D7: =Annahmen!$B$14/((Annahmen!$B$10*D$3*(0.37*$A7+0.63*(Annahmen!$B$19*10/15+Annahmen!$B$20*5/15)))-Annahmen!$B$15) -> 9.7775242 | E7: =Annahmen!$B$14/((Annahmen!$B$10*E$3*(0.37*$A7+0.63*(Annahmen!$B$19*10/15+Annahmen!$B$20*5/15)))-Annahmen!$B$15) -> 8.8233306
A8: 0.4 | B8: =Annahmen!$B$14/((Annahmen!$B$10*B$3*(0.37*$A8+0.63*(Annahmen!$B$19*10/15+Annahmen!$B$20*5/15)))-Annahmen!$B$15) -> 11.180811 | C8: =Annahmen!$B$14/((Annahmen!$B$10*C$3*(0.37*$A8+0.63*(Annahmen!$B$19*10/15+Annahmen!$B$20*5/15)))-Annahmen!$B$15) -> 9.8367081 | D8: =Annahmen!$B$14/((Annahmen!$B$10*D$3*(0.37*$A8+0.63*(Annahmen!$B$19*10/15+Annahmen!$B$20*5/15)))-Annahmen!$B$15) -> 8.781088 | E8: =Annahmen!$B$14/((Annahmen!$B$10*E$3*(0.37*$A8+0.63*(Annahmen!$B$19*10/15+Annahmen!$B$20*5/15)))-Annahmen!$B$15) -> 7.9300768
A10: Hinweise:
A11: ="• Basis-Szenario (32 ct/kWh, 100% Ertrag): "&ROUND(D6,2)&" Jahre Amortisation (PVGIS-Daten: 7,2 Jahre)" -> • Basis-Szenario (32 ct/kWh, 100% Ertrag): 10,49 Jahre Amortisation (PVGIS-Daten: 7,2 Jahre)
A12: • Bei sinkendem Verbrauch (Kinder ziehen aus) verschlechtert sich die Wirtschaftlichkeit leicht
A13: • Bei steigenden Strompreisen amortisiert sich die Anlage deutlich schneller
A14: • Selbst bei nur 80% des erwarteten Ertrags liegt die Amortisation unter 15 Jahren

Sheet Annahmen
A1: DETAILLIERTE ANNAHMEN DER BERECHNUNG
A3: Standort & Anlage
A4: PLZ | B4: 55545 (Bad Kreuznach)
A5: Dachausrichtung | B5: Nord-Nord-Ost (24° West)
A6: Dachneigung | B6: 30°
A7: Verfügbare Dachfläche | B7: ca. 100 m² (effektiv ~80 m² nutzbar)
A8: Installierte Leistung | B8: =Übersicht!D5 -> 16.56 | C8: 15.48
A9: Spezifischer Ertrag (PVGIS / Jahr) | B9: 753
A10: Jährlicher Ertrag (Jahr 1) | B10: 11297
A11: Degradation pro Jahr | B11: 0.005
A13: Kosten
A14: Investitionskosten (1.300 €/kWp, Vollinstallation) | B14: 18007.88
A15: Betriebskosten pro Jahr (Wartung, Versicherung) | B15: 150
A17: Vergütung & Preise
A18: Strompreis (Bezug) | B18: 0.32
A19: Einspeisevergütung (0-10 kWp) | B19: 0.0778
A20: Einspeisevergütung (>10 kWp) | B20: 0.0673
A22: Verbrauchsszenarien
A23: Jahre 1-5 | B23: 21.000 kWh (WP 7.500 + Autos 9.000 + Haushalt 4.500)
B24: Eigenverbrauchsquote: 40%
A25: Jahre 6-10 | B25: 18.000 kWh (WP 7.500 + Autos 6.000 + Haushalt 4.500)
B26: Eigenverbrauchsquote: 35%
A27: Jahre 11-20 | B27: 15.000 kWh (WP 7.500 + Autos 3.000 + Haushalt 4.500)
B28: Eigenverbrauchsquote: 30%
A30: Bestandsanlage (Südseite)
A31: Installierte Leistung | B31: 11.28
A32: Inbetriebnahme | B32: 2012
A33: Jährlicher Ertrag | B33: 12000
A34: Eigenverbrauch (kein Akku) | B34: 0.3
A35: Einspeisevergütung | B35: 0.18
A36: Restlaufzeit | B36: =2013+20-YEAR(TODAY()) -> 7
A38: Finanzielle Parameter
A39: Diskontierungssatz | B39: 0.03
A40: Betrachtungszeitraum | B40: 20
A41: Inflationsanpassung | B41: nicht berücksichtigt (konservativ)
